{"cameraMode":{"drawMode":0,"name":"Shaded","section":"Shading Mode"},"sceneLighting":true,"audioPlay":false,"sceneViewState":{"m_AlwaysRefresh":false,"showFog":true,"showSkybox":true,"showFlares":true,"showImageEffects":true,"showParticleSystems":true,"showVisualEffectGraphs":true,"m_FxEnabled":true},"in2DMode":false,"pivot":{"x":-3.6353654861450197,"y":-0.9135191440582275,"z":1.4087047576904297},"rotation":{"x":0.191898912191391,"y":-0.27040284872055056,"z":0.055096764117479327,"w":0.941830575466156},"size":5.121641159057617,"orthographic":false}